setup.py
html/entities.py
micropython_html.entities.egg-info/PKG-INFO
micropython_html.entities.egg-info/SOURCES.txt
micropython_html.entities.egg-info/dependency_links.txt
micropython_html.entities.egg-info/top_level.txt