Metadata-Version: 1.0
Name: micropython-html.entities
Version: 3.3.3
Summary: CPython html.entities module ported to MicroPython
Home-page: https://github.com/micropython/micropython/issues/405
Author: MicroPython Developers
Author-email: micro-python@googlegroups.com
License: Python
Platform: UNKNOWN
